djangocric/__init__.py
djangocric/admin.py
djangocric/apps.py
djangocric/models.py
djangocric/tests.py
djangocric/urls.py
djangocric/views.py
djangocric/migrations/__init__.py
djangocric/migrations/__pycache__/__init__.cpython-37.pyc
djangocric/migrations/__pycache__/__init__.cpython-38.pyc
djangocric/templates/djangoadmin/djangocric/djangocric_homepage.html
djangocric/templates/djangoadmin/djangocric/search_live_score_detail.html
djangocric/templates/djangoadmin/djangocric/search_match_summary_detail.html
djangocric-1.0.1.dist-info/License
djangocric-1.0.1.dist-info/METADATA
djangocric-1.0.1.dist-info/WHEEL
djangocric-1.0.1.dist-info/top_level.txt
djangocric-1.0.1.dist-info/RECORD
